CHANGES.txt
LICENCE.txt
MANIFEST.in
README.md
VERSION.txt
requirements.txt
setup.py
bin/jobmanager-api
jobmanager/API.VERSION.txt
jobmanager/__init__.py
jobmanager/api.py
jobmanager/static/favicon.ico
jobmanager/static/css/common.live.css
jobmanager/static/css/host.live.css
jobmanager/static/css/host.live2.css
jobmanager/static/css/index.css
jobmanager/static/css/job.live.css
jobmanager/static/css/log.live.css
jobmanager/static/css/lib/tooltipster-sideTip-borderless.min.css
jobmanager/static/css/lib/tooltipster-sideTip-jobmanager.min.css
jobmanager/static/css/lib/tooltipster.bundle.min.css
jobmanager/static/js/common.live.js
jobmanager/static/js/host.live.js
jobmanager/static/js/host.live2.js
jobmanager/static/js/job.live.js
jobmanager/static/js/log.live.js
jobmanager/static/js/lib/tooltipster.bundle.min.js
jobmanager/templates/index.html
jobmanager/templates/common/base.html
jobmanager/templates/host/live.html
jobmanager/templates/host/live2.html
jobmanager/templates/job/live.html
jobmanager/templates/log/live.html
jobmanager_api.egg-info/PKG-INFO
jobmanager_api.egg-info/SOURCES.txt
jobmanager_api.egg-info/dependency_links.txt
jobmanager_api.egg-info/top_level.txt