Metadata-Version: 1.1
Name: jobmanager-api
Version: 0.13.10
Summary: Job Manager API
Home-page: https://github.com/ronhanson/python-jobmanager-api
Author: Ronan Delacroix
Author-email: ronan.delacroix@gmail.com
License: The MIT License (MIT)
